CaesarCipher/Cipher.py
CaesarCipher/__init__.py
CaesarCipher_Zoma-0.1.0.dist-info/METADATA
CaesarCipher_Zoma-0.1.0.dist-info/WHEEL
CaesarCipher_Zoma-0.1.0.dist-info/top_level.txt
CaesarCipher_Zoma-0.1.0.dist-info/RECORD
